ikarus/__init__.py
ikarus/_src.py
ikarus/dataverse_github.py
ikarus/test_dataverse_github.py
ikarus/test_src.py
ikarus/test_utils.py
ikarus/utils.py
ikarus/baselines/__init__.py
ikarus/baselines/qmt_baselines.py
ikarus/baselines/riann/__init__.py
ikarus/baselines/riann/riann.onnx
ikarus/baselines/riann/riann.py
ikarus/benchmark/__init__.py
ikarus/benchmark/_benchmark.py
ikarus/benchmark/xmls/arm.xml
ikarus/benchmark/xmls/gait.xml
imt_ikarus-1.2.1.dist-info/METADATA
imt_ikarus-1.2.1.dist-info/WHEEL
imt_ikarus-1.2.1.dist-info/top_level.txt
imt_ikarus-1.2.1.dist-info/RECORD
