Metadata-Version: 2.1
Name: imt-ikarus
Version: 1.2.1
Summary: IKArus - Inertial and Optical Data of Kinematic ChAin Motion
Author-email: Simon Bachhuber <simon.bachhuber@fau.de>
Project-URL: Homepage, https://github.com/SimiPixel/ikarus
Project-URL: Issues, https://github.com/SimiPixel/ikarus/issues
Classifier: Programming Language :: Python :: 3
Classifier: License :: OSI Approved :: MIT License
Classifier: Operating System :: OS Independent
Requires-Python: >=3.10
Requires-Dist: numpy
Requires-Dist: qmt
Requires-Dist: scipy
Requires-Dist: dm-tree
Requires-Dist: requests
Requires-Dist: pandas
Requires-Dist: imt-tree-utils
Provides-Extra: baselines
Requires-Dist: onnxruntime ; extra == 'baselines'
Provides-Extra: benchmark
Requires-Dist: imt-ring ; extra == 'benchmark'
